README.md
setup.py
zipa/__init__.py
zipa/entity.py
zipa/magic.py
zipa/module.py
zipa/resource.py
zipa/utils.py
zipa.egg-info/PKG-INFO
zipa.egg-info/SOURCES.txt
zipa.egg-info/dependency_links.txt
zipa.egg-info/requires.txt
zipa.egg-info/top_level.txt