Metadata-Version: 1.1
Name: zipa
Version: 0.3.6
Summary: General purpose REST API client
Home-page: https://github.com/Presslabs/zipa
Author: Presslabs SRL
Author-email: support@presslabs.com
License: UNKNOWN
Platform: any
Classifier: Programming Language :: Python :: 2.7
Classifier: Programming Language :: Python :: 3.4
Classifier: Programming Language :: Python :: 3.5
